ProgrammingAndProgrammingLanguagesBrownUniv/README.md
ProgrammingAndProgrammingLanguagesBrownUniv/__init__.py
ProgrammingAndProgrammingLanguagesBrownUniv/__main__.py
ProgrammingAndProgrammingLanguagesBrownUniv/file.epub
ProgrammingAndProgrammingLanguagesBrownUniv/index.html
ProgrammingAndProgrammingLanguagesBrownUniv/css/__init__.py
ProgrammingAndProgrammingLanguagesBrownUniv/css/annotations.css
ProgrammingAndProgrammingLanguagesBrownUniv/css/main.css
ProgrammingAndProgrammingLanguagesBrownUniv/css/normalize.css
ProgrammingAndProgrammingLanguagesBrownUniv/css/popup.css
ProgrammingAndProgrammingLanguagesBrownUniv/font/__init__.py
ProgrammingAndProgrammingLanguagesBrownUniv/font/fontello.eot
ProgrammingAndProgrammingLanguagesBrownUniv/font/fontello.svg
ProgrammingAndProgrammingLanguagesBrownUniv/font/fontello.ttf
ProgrammingAndProgrammingLanguagesBrownUniv/font/fontello.woff
ProgrammingAndProgrammingLanguagesBrownUniv/img/__init__.py
ProgrammingAndProgrammingLanguagesBrownUniv/img/annotator-glyph-sprite.png
ProgrammingAndProgrammingLanguagesBrownUniv/img/annotator-icon-sprite.png
ProgrammingAndProgrammingLanguagesBrownUniv/img/apple-touch-icon.png
ProgrammingAndProgrammingLanguagesBrownUniv/img/cancelfullscreen.png
ProgrammingAndProgrammingLanguagesBrownUniv/img/close.png
ProgrammingAndProgrammingLanguagesBrownUniv/img/fullscreen.png
ProgrammingAndProgrammingLanguagesBrownUniv/img/loader.gif
ProgrammingAndProgrammingLanguagesBrownUniv/img/menu-icon.png
ProgrammingAndProgrammingLanguagesBrownUniv/img/save.png
ProgrammingAndProgrammingLanguagesBrownUniv/img/saved.png
ProgrammingAndProgrammingLanguagesBrownUniv/img/settings-s.png
ProgrammingAndProgrammingLanguagesBrownUniv/img/settings.png
ProgrammingAndProgrammingLanguagesBrownUniv/img/star.png
ProgrammingAndProgrammingLanguagesBrownUniv/js/__init__.py
ProgrammingAndProgrammingLanguagesBrownUniv/js/epub.js
ProgrammingAndProgrammingLanguagesBrownUniv/js/epub.min.js
programming_and_programming_languages_brown_univ-2024.3.2.0.dist-info/METADATA
programming_and_programming_languages_brown_univ-2024.3.2.0.dist-info/WHEEL
programming_and_programming_languages_brown_univ-2024.3.2.0.dist-info/entry_points.txt
programming_and_programming_languages_brown_univ-2024.3.2.0.dist-info/top_level.txt
programming_and_programming_languages_brown_univ-2024.3.2.0.dist-info/RECORD
